{
  "schemaVersion": 1,
  "id": "cubiomes_integrated",
  "version": "${version}",
  "name": "Cubiomes Integrated",
  "description": "In-game seed search dashboard powered by cubiomes + Fabric.",
  "authors": [
    "Cubiomes Integrated"
  ],
  "license": "MIT",
  "environment": "*",
  "entrypoints": {
    "main": [
      "dev.cubiomes.integrated.CubiomesIntegratedMod"
    ],
    "client": [
      "dev.cubiomes.integrated.client.CubiomesIntegratedClient"
    ]
  },
  "depends": {
    "fabricloader": ">=0.16.0",
    "minecraft": "~1.21.1",
    "java": ">=21",
    "fabric-api": "*"
  }
}
